{
  "type": "visual",
  "timestamp": "2026-03-26T02:52:38.387533",
  "backend": "llava",
  "description": "The image captures a tranquil scene set in a dimly lit room. The room's walls are painted white, providing a stark contrast to the black furniture that dominates the space. A dark couch sits against one wall, its form just discernible in the subdued lighting.\n\nIn front of the couch, a coffee table takes center stage. It's here that we find our main subjects - a solitary soda can and an empty bottle of beer. The objects are stationary, biding their time until they're needed again.\n\nOn the far wall of the room, two windows punctuate the expanse of white. They're adorned with yellow curtains that flutter slightly, suggesting a gentle breeze might be at play. A window sill rests under each window, hosting small plants that add a touch of life to the otherwise stark decor.\n\nThe room is devoid of human presence, yet it's filled with subtle details that tell a story of quiet nights spent in solitude or perhaps shared conversations over cold drinks on the couch. The overall atmosphere is one of calm and comfort, an intimate snapshot into someone's personal space.",
  "frame_path": "/Users/v/other/astrid/capsules/perception/workspace/visual/frame_2026-03-26T02-52-28.227865.jpg"
}