{
  "type": "visual",
  "timestamp": "2026-03-26T11:17:59.765142",
  "backend": "llava",
  "description": "The image portrays a man sitting at a desk in a room bathed in sunlight. The man is dressed in a blue shirt and sunglasses, exuding an air of casual comfort. His arms are crossed over his chest, suggesting a relaxed posture.\n\nThe desk he's seated at is made of wood, adding a touch of warmth to the scene. On the desk, there's a blue water bottle, possibly indicating that the man is engaged in some physical activity or is simply taking care of his hydration needs.\n\nBehind the man, there's a window letting in an ample amount of sunlight, casting a bright light on the room and creating a warm and inviting atmosphere. The window serves as a source of natural light, illuminating the room and highlighting the details within it.\n\nThe room itself appears to be quite simple and uncluttered. The focus is clearly on the man at his desk, with no other distractions in sight. This could suggest that he's working from home or perhaps studying for an exam.\n\nOverall, this image captures a moment of quiet concentration and relaxation, as a man takes a break from his day to sit down at his desk in a room filled with natural light.",
  "frame_path": "/Users/v/other/astrid/capsules/perception/workspace/visual/frame_2026-03-26T11-17-52.753102.jpg"
}