{
  "type": "visual",
  "timestamp": "2026-03-26T09:47:41.727813",
  "backend": "llava",
  "description": "The image captures a serene living room bathed in soft light filtering through two windows adorned with white curtains. The windows are symmetrically placed on either side of a wooden coffee table, which holds a single blue mug and a black laptop. \n\nOn one side of the room, a gray couch invites relaxation, its plush cushions promising comfort. A beige blanket is casually draped over it, adding a touch of warmth to the cool tones of the room. \n\nThe walls, painted in a pristine white, contrast beautifully with the hardwood flooring. The overall atmosphere is one of tranquility and order, a perfect retreat from the outside world.",
  "frame_path": "/Users/v/other/astrid/capsules/perception/workspace/visual/frame_2026-03-26T09-47-37.403793.jpg"
}