{
  "type": "visual",
  "timestamp": "2026-03-26T21:57:47.575504",
  "backend": "llava",
  "description": "In the quiet solitude of a dimly lit room, a man finds comfort on a couch, his attention captivated by the television screen before him. The room is bathed in soft, muted colors, creating an atmosphere of calm and relaxation. \n\nThe man, dressed in casual attire, is seated comfortably on the right side of the couch. His posture suggests he's deeply engrossed in whatever is playing out on the screen. A coffee table rests in front of him, its surface home to a single can of soda. The can's vibrant color stands out against the otherwise subdued palette of the room.\n\nBehind the man, a window punctuates the wall, its glass pane reflecting the soft glow of ambient light. A curtain hangs from it, partially drawn back to let in just enough light to illuminate the room without overpowering it.\n\nThe overall scene paints a picture of tranquility and leisure, as if time has slowed down for this moment alone. It's a snapshot of everyday life, captured in all its simple beauty.",
  "frame_path": "/Users/v/other/astrid/capsules/perception/workspace/visual/frame_2026-03-26T21-57-41.525353.jpg"
}