{
  "type": "visual",
  "timestamp": "2026-03-26T14:46:46.270157",
  "backend": "llava",
  "description": "In this image, a man and his dog are sharing a moment in a cozy living room bathed in natural light. The man, dressed in a black shirt with red text, stands on a wooden coffee table. He holds a blue cup in one hand and a phone to his ear with the other, seemingly engrossed in conversation.\n\nOn the gray couch opposite him, the dog is comfortably resting, its head gently placed on the armrest. The couch's plush cushions provide a stark contrast to the man's hard surface stance on the coffee table.\n\nThe room itself is simple yet inviting. A window allows sunlight to stream in from the right side of the image, casting warm hues across the scene. In the background, you can see a white wall and a bookshelf, adding to the homely atmosphere.\n\nThe relative positions of the objects tell their own story - a man multitasking between his phone call and perhaps enjoying some coffee, while his faithful companion takes advantage of this quiet moment for a nap on the comfortable couch. It's a snapshot of everyday life, captured beautifully in this image.",
  "frame_path": "/Users/v/other/astrid/capsules/perception/workspace/visual/frame_2026-03-26T14-46-35.819872.jpg"
}