{
  "type": "visual",
  "timestamp": "2026-03-26T08:46:34.801109",
  "backend": "llava",
  "description": "In the image, a man is seated at a desk in a room bathed in bright sunlight. He's wearing a yellow sweater and headphones, suggesting he might be listening to something or perhaps working on an audio project. The desk is positioned against a wall with a window, through which the sun is shining, creating a warm and inviting atmosphere.\n\nThe man appears to be deep in thought as he sits at his desk. In front of him is a laptop, open and ready for use. To his side, there's a coffee cup, perhaps filled with a hot beverage to keep him company during his work or contemplation.\n\nIn the background, there's another person who seems to be out of focus, adding a sense of depth and activity to the scene. The precise locations of objects are hard to determine due to the bright sunlight and the angle of the image, but it's clear that this is an indoor setting with natural light streaming in through the window.\n\nThe image captures a moment of quiet concentration amidst what appears to be a bustling environment. It's a snapshot of modern life, where work and personal moments often blend together in shared spaces. The bright colors, the sunlight, and the arrangement of objects all contribute to creating an atmosphere that is both professional and comfortable.",
  "frame_path": "/Users/v/other/astrid/capsules/perception/workspace/visual/frame_2026-03-26T08-46-22.637157.jpg"
}