{
  "type": "visual",
  "timestamp": "2026-03-27T08:48:21.315705",
  "backend": "llava",
  "description": "The image captures a tranquil indoor setting. Dominating the scene is a white brick wall that houses a black fireplace with a white mantel. The fireplace, though not in use, adds a touch of rustic charm to the room. \n\nAbove the fireplace hangs a television screen, which is currently turned off. The screen is mounted securely on the wall, ready to display its content at the flick of a switch. \n\nThe perspective of the image is particularly striking. Taken from below, it offers an upward view of the fireplace and television screen, lending a sense of grandeur to these everyday objects. It's as if we're looking up at them, appreciating their presence in our space.\n\nDespite the simplicity of the scene, there's a certain warmth to it. The brick wall, the black fireplace, and the white mantel all contribute to creating an atmosphere that feels cozy and inviting. It's a snapshot of everyday life, captured in vivid detail.",
  "frame_path": "/Users/v/other/astrid/capsules/perception/workspace/visual/frame_2026-03-27T08-48-09.858830.jpg"
}