{
  "type": "visual",
  "timestamp": "2026-03-26T09:12:31.993958",
  "backend": "llava",
  "description": "This image captures a serene moment in a living room. At the center of the scene, a man is comfortably seated on a blue couch, engrossed in his phone which he holds in his hands. He's casually dressed in a blue shirt and sporting a baseball cap with a playful red pom-pom on top.\n\nThe room around him is softly lit by natural light filtering through a window adorned with white curtains. The white walls of the room add to the calm atmosphere, reflecting the light and enhancing the sense of space.\n\nOn an end table next to the couch, there's a black coffee table. On it, there's a blue cup, perhaps holding a warm beverage for the man to enjoy while he interacts with his phone.\n\nOverall, this image paints a picture of a relaxed afternoon spent in the comfort of one's own home.",
  "frame_path": "/Users/v/other/astrid/capsules/perception/workspace/visual/frame_2026-03-26T09-12-22.277686.jpg"
}