{
  "type": "visual",
  "timestamp": "2026-03-26T20:41:43.362516",
  "backend": "llava",
  "description": "In the heart of a dimly lit room, a solitary figure finds solace on a couch, their form illuminated by the soft glow of a single candle. The candle, perched on a small table to the left, casts long shadows that dance upon the wall behind it. \n\nThe person is seated comfortably, legs crossed in a relaxed manner. Their arms rest gently on the armrests, fingers lightly curled as they cradle a glass of wine. The glass, filled with a rich red liquid, reflects the warm light from the candle, adding to the intimate ambiance.\n\nTo the right, an open window offers a tantalizing glimpse into another world. The darkness outside contrasts starkly with the room's interior, creating a captivating visual juxtaposition. The scene is devoid of text and other objects, focusing solely on the person and their solitary moment of quiet reflection.",
  "frame_path": "/Users/v/other/astrid/capsules/perception/workspace/visual/frame_2026-03-26T20-41-37.927989.jpg"
}